llm_rewards/__init__.py
llm_rewards/base.py
llm_rewards/reward_fn.py
llm_rewards/stack.py
llm_rewards/rewards/__init__.py
llm_rewards/rewards/format_reward.py
llm_rewards/rewards/length_reward.py
llm_rewards/rewards/relevance_reward.py
llm_rewards/rewards/reward_model.py
llm_rewards/rewards/similarity_reward.py
llm_rewards/rewards/simple_think_reward.py
llm_rewards/rewards/xml_reward.py
llm_rewards/utils/__init__.py
llm_rewards-0.0.1.dist-info/METADATA
llm_rewards-0.0.1.dist-info/WHEEL
llm_rewards-0.0.1.dist-info/top_level.txt
llm_rewards-0.0.1.dist-info/RECORD
